Workbook

Sheet Sheet1
B2: Er. SUNIL KUMAR | I2: # 304, Village: Daria,
B3: SURVEYOR & LOSS ASSESSOR | I3: Near Railway Station, Chandigarh
B4: LICENCE NO: 73070 EXPIRY: 08.02.2028 | I4: Mobile: 098761-35253
B5: PAN NO: AQUPK1480C | I5: e-mail:- ksunilsurveyor@gmail.com
B8: Ref: | C8: final | J8: Date:
B10: PRIVATE & CONFIDENTIAL SURVEY REPORT
B11: The report is issued by me as Licenced surveyor without prejudice in respect of cause, nature & extent of loss/damages and subject to the terms and conditions of Insurance Policy.
B13: 1 | C13: INSURERS | F13: : | G13: UNITED INDIA INSURANCE CO. LTD. | J13: IDV= | K13: 638000
C14: ADDRESS | F14: : | G14: NEAR GOVT HIGH SCHOOL, HANDLOOM STREET SURGAPURI KOTKAPURA, DISTT.FARIDKOT KOTKAPURA, FARIDKOT, PB 151204 | W14: 98131- | X14: Nitu | Y14: udaanaaa
W15: 64284
C16: COVER NOTE/POLICY NO. | F16: : | G16: 2012823125P111997595 | I16: Period: | L16: 27/10/2025 to 26/10/2026 | N16: 231390
B18: 2 | C18: INSURED | F18: : | G18: MR BALKAR SINGH
C19: ADDRESS | F19: : | G19: H NO B-9/939 W NO 20 KOTKAPURA SURG, PURI NEAR GOVT SCHOOL, FARIDKOT, PB, 151204
C20: CONTACT NO. | F20: : | G20: 9888902800
B22: 3 | C22: HPA WITH | F22: : | G22: AU SMALL FINANCE BANK LTD
B24: 4 | C24: VEHICLE PARTICULARS | F24: : | G24: RC Original Checked & Found In Order
C25: Registration No. / RTO | F25: : | G25: PB03BH1786 / RTO: RTO FEROZ
C26: Date of Registration issue | F26: : | G26: 22/10/2021
C27: Date of Registration expiry | F27: : | G27: 21/10/2036
C28: Chassis No | F28: : | G28: MA3BNC22SMK395069 | I28: Physically Checked
C29: Engine No | F29: : | G29: K15BN1234400
C30: Make & Year of Manufacturer | F30: : | G30: MARUTI SUZUKI / ERTIGA SMART HYBRID VXI 1.5L SMT
C31: Type of Body | F31: : | G31: RIGID (PASSENGER CAR)
C32: Class of Vehicle | F32: : | G32: Motor Car
C33: Pre-Accident Condition | F33: : | G33: GOOD
C34: Registered Laden Weight | F34: : | G34: 1795
C35: Unladen Weight | F35: : | G35: 1235
C36: Fitness Cert. Valid upto | F36: :
C37: Permit No. / Authorization No. | F37: : | G37: Permit No: PB2024-AITP-2340A / Auth No: AZ/PB/1/032024/12398
C38: Permit Validity / Authorization Validity | F38: : | G38: Permit: 10/03/2029 / Auth: 11/03/2025
C39: Type of Permit | F39: : | G39: TOURIST PERMIT (TVP(MOTOR CAB))-AIR-CONDITIONER
C40: Route/area of Operation | F40: : | G40: Whole India
C41: Seating Capacity | F41: : | G41: 7
C42: Road Tax Paid Upto | F42: : | G42: 31.05.2026
C43: Fuel Used | F43: : | G43: PETROL/CNG
C44: Colour | F44: : | G44: PEARL ARCTIC WHITE
C45: Name of Regd. Owner as per RC | F45: : | G45: BALKAR SINGH
B47: 5 | C47: DRIVER'S PARTICULARS | F47: : | G47: DL Original Checked & Found In Order
C48: Name of Driver | F48: : | G48: BALKAR SINGH | J48: DOB: | K48: 01/10/1972
C49: Address | F49: :
C50: LICENCE NO. | F50: : | G50: PB-0420130022279
C51: Date of issue | F51: : | G51: 03/04/2013
C52: Valid Till | F52: : | G52: NTR: 30/09/2032 | TR: 15/12/2027
C53: Issuing Authority | F53: : | G53: FARIDKOT RTA
C54: Type of Licence | F54: : | G54: MCWG, LMV, TRANS
B56: 6 | C56: ACCIDENT HISTORY
C57: Date of Accident | F57: : | G57: 07/04/2026 | Time: 5:30 AM | N57: 18.06.2023
C58: Place of Accident | F58: : | G58: Rohtak, Haryana
B60: 7 | C60: DETAIL OF SURVEY
C61: Date of Allotment of Survey | F61: : | G61: 09/04/2026
C62: Date and Time of Survey | F62: : | G62: 26/05/2026 | H62: and onwards | I62: times ofs serveys | J62: 0.4375
C63: Date of Spot Survey Report Recd. | F63: : | G63: 26/03/2026
C64: Person Present at the Time of Survey | F64: : | G64: Repairer was present
B66: 8 | C66: PLACE OF SURVEY | G66: SM Auto Care Centre, Opp. I.T.I., G. T. Road, Moga -142 001 (Pb.)
C67: Workshop | F67: : | G67: SM Auto Care Centre, Opp. I.T.I., G. T. Road, Moga -142 001 (Pb.)
C68: Address | F68: :
C69: Status | F69: :
B71: 9 | C71: FIR DETAIL | F71: : | G71: No: 098 | Dt: 05/07/2025 | PS: PS SECTOR 19
B73: 10 | C73: INJURY/THIRD PARTY LOSS | F73: : | G73: NA
B75: 11 | C75: CAUSE AND NATURE OF ACCIDENT
C76: As stated in the Claim Form,
B79: 12 | C79: OBERVATIONS/COMMENTS
C80: As per the instructions of The Oriental Insurance Co Ltd, RO:-Service Centre, Sector-17, Chandigarh. I visited the Repairer's workshop. The Vehicle was carefully inspected, its damages were noted and photographs taken. The Photographs in the Under Repair Condition were also taken. The damages are commensurate with the cause and nature of accident.
B82: 13 | C82: MAIN DAMAGES
B85: 14 | C85: NOTES:
B86: 1 | C86: Case allotted by The Oriental Insurance Co Ltd, RO: Service Centre, Sector-17, Chandigarh
B87: 2 | C87: The loss of damage or liability has arisen proximately caused by the insured peril.
B88: 3 | C88: None of the exclusion under the policy has is caused loss of damage or liability.
B89: 4 | C89: The salvage of the vehicle has been destroyed/crushed in the presence of the Repairer.
B90: 5 | C90: Re-inspection too has been done by me. All the replacemnets of parts and repair job have been dully carried out.
B91: 6 | C91: At the time of survey, I talked with Insured and discussed about the loss. About the loss, Insured told me the same which is mentioned in the Claim Form.
B93: 15 | C93: DETAIL OF ASSESSMENT
B95: CUBIC CAPACITY | F95: 1248 | G95: SO, EXCESS CLAUSE (IN RS.) | J95: 1000
B96: LIFE OF VEHICLE ( IN YEARS ) | F96: =E250 -> 0 | G96: SO, DEP. ON METAL (IN %) | J96: =IF(F96<0.5,0,IF(F96<1,5,IF(F96<2,10,IF(F96<3,15,IF(F96<4,25,IF(F96<5,35,IF(F96<10,40,50))))))) -> 0
B97: GSTIN (IN %) FOR PARTS | F97: 18 | G97: GSTIN (IN %) FOR LABOUR | J97: 18
B100: S.N. | C100: Part Discription | F100: Estimated | G100: Metal | H100: Plastic | I100: Glass
B101: 1 | C101: BOLT FRT HOOD HINGE | F101: 45
B102: 2 | C102: BOLT | F102: 35
B103: 3 | C103: SCREW | F103: 27.6
B104: 4 | C104: SCREW | F104: 45
B105: 5 | C105: NUT | F105: 60 | G105: 45.72 | K105: 1
B106: 6 | C106: BOLT,8X20 | F106: 1320
B107: 7 | C107: SCREW,FR BUMPER SIDE | F107: 60
B108: 8 | C108: NUT | F108: 100 | G108: 11.86 | K108: 2
B109: 9 | C109: PIN,CAMSHAFT PULLEY DOWEL | F109: 3.5
B110: 10 | C110: GROMMET,FRONT HOOD | F110: 31.5
B111: 11 | C111: CLAMP | F111: 8
B112: 12 | C112: .CLIP,COWL TOP SIDE GARNISH | F112: 18 | H112: 18 | J112: 36.66 | K112: 76
B113: 13 | C113: CLIP,TRUNK ROOM SIDE TRIM | F113: 60
B114: 14 | C114: CLIP | F114: 120 | H114: 120 | J114: 83.1 | K114: 6
B115: 15 | C115: BULB | F115: 86 | H115: 72.88 | K115: 7
B116: 16 | C116: BULB (12V60W,HB3) | F116: 770 | H116: 326.27 | K116: 8
B117: 17 | C117: BULB (12V, WY21W) | F117: 300
B118: 18 | C118: HALF ENGINE | F118: 92533
B119: 19 | C119: GASKET, CYLINDER HEAD | F119: 603.5
B120: 20 | C120: COVER ASSY, CYLINDER HEAD | F120: 1862 | G120: 1577.96 | K120: 10
B121: 21 | C121: GASKET,CYLINDER HEAD COVER | F121: 198
B122: 22 | C122: HOSE, BREATHER | F122: 34
B123: 23 | C123: PLUG OIL DRAIN | F123: 43 | G123: 36.44 | K123: 11
B124: 24 | C124: MOUNTING,ENG LH | F124: 2055.5 | G124: 1741.94 | K124: 12
...

Sheet Sheet2
G3: MOTOR SURVEY REPORT
B7: INSURER | F7: UNITED INDIA INSURANCE CO. LTD.
B8: ADDRESS | F8: Chowk No-1, Gol Market, Jaitu, Faridkot-151202, Punjab
F9: =Sheet1!G15 -> 0
B12: INSURED | F12: MR BALKAR SINGH
B14: VEHICLE REG. NO. | F14: PB03BH1786
B16: C.NOTE/POLICY NO. | F16: 2012823125P111997595
B18: PERIOD | F18: 27/10/2025 to 26/10/2026
B20: DATE OF LOSS | F20: 07/04/2026
B28: PAYMENT TO BE MADE IN THE FAVOUR OF REPAIRER
B44: REPORT SUBMITTED BY:
B48: Er. SUNIL KUMAR | G48: # 304, Village: Daria,
B49: SURVEYOR & LOSS ASSESSOR | G49: Near Railway Station, Chandigarh
B50: LICENCE NO: 73070 EXPIRY: 08.02.2028 | G50: Mobile: 098761-35253
B51: PAN NO: AQUPK1480C | G51: e-mail:- ksunilsurveyor@gmail.com

Sheet Sheet5
C3: Er. SUNIL KUMAR | J3: # 304, Village: Daria,
C4: SURVEYOR & LOSS ASSESSOR | J4: Near Railway Station, Chandigarh
C5: LICENCE NO: 73070 EXPIRY: 08.02.2028 | J5: Mobile: 098761-35253
C6: PAN NO: AQUPK1480C | J6: E-mail: ksunilsurveyor@gmail.com
C10: Ref: | D10: final | K10: Date: | L10: =Sheet1!K8 -> 0
F12: SURVEY FEE BILL
C15: INSURED | F15: MR BALKAR SINGH | G15: =Sheet1!G18 -> MR BALKAR SINGH
G16: =Sheet1!G19 -> H NO B-9/939 W NO 20 KOTKAPURA SURG, PURI NEAR GOVT SCHOOL, FARIDKOT, PB, 151204
C18: INSURERS | F18: UNITED INDIA INSURANCE CO. LTD. | G18: =Sheet1!G13 -> UNITED INDIA INSURANCE CO. LTD.
G19: =Sheet1!G14 -> NEAR GOVT HIGH SCHOOL, HANDLOOM STREET SURGAPURI KOTKAPURA, DISTT.FARIDKOT KOTKAPURA, FARIDKOT, PB 151204
G20: =Sheet1!G15 -> 0
C22: VEHICLE/ITEM | F22: PB03BH1786 | G22: =Sheet1!G25 -> PB03BH1786 / RTO: RTO FEROZ
C23: Make & Year of Manufacturer | F23: MARUTI SUZUKI / ERTIGA SMART HYBRID VXI 1.5L SMT | G23: =Sheet1!G30 -> MARUTI SUZUKI / ERTIGA SMART HYBRID VXI 1.5L SMT
C25: C NOTE/POLICY NO. | F25: 2012823125P111997595 | G25: =Sheet1!G16 -> 2012823125P111997595 | J25: Period: | K25: =Sheet1!J16 -> 0
C28: PROFESSIONAL FEE | G28: Rs | H28: 1800
C30: CONVEYANCE CHARGES | G30: Rs | H30: 500
C32: PHOTOGRAPHS | E32: (12x10=120.00) | G32: Rs | H32: 120
C33: (Digital Photographs)
C35: DAILY ALLOWANCE | G35: Rs | H35: 0
C37: MISCELLANEOUS | G37: Rs | H37: 0
H38: ----------------------
F39: TOTAL | G39: Rs | H39: =SUM(H28:H37) -> 2420
H40: ----------------------
C44: INLYAS CODE: | E44: GH0000046246
C48: FOR NEFT PAYMENT | J48: (SUNIL KUMAR)
C50: BANK ACCOUNT DETAILS
C51: BANK NAME: | E51: BANK OF INDIA
C52: A/C NUMBER: | E52: 620110110000751
C53: A/C TYPE: | E53: SAVING
C54: IFSC CODE: | E54: BKID0006201
C55: MICRO CODE: | E55: 160013003

Sheet Sheet6
B4: ITEM WISE BREAK UP DETAILS IN SETTLEMENT SHEET
B6: ITEM DESCRIPTION | D6: NET AMOUNT (AFTER DEP.) | E6: GST % | F6: GST AMOUNT
B7: Labour | D7: =Sheet1!I174 -> 0 | E7: 18 | F7: =D7*E7/100 -> 0
B8: Parts Metallic | D8: =Sheet1!G145 -> 0 | E8: 28 | F8: =D8*E8/100 -> 0
B9: Parts Metallic | D9: 0 | E9: 18 | F9: =D9*E9/100 -> 0
B10: Parts Non-Metallic | D10: =Sheet1!I145 -> 0 | E10: 18 | F10: =D10*E10/100 -> 0
B11: Plastic | D11: =Sheet1!H145 -> 165.25 | E11: 28 | F11: =D11*E11/100 -> 46.27
B12: Glass | D12: =Sheet1!J145 -> 0 | E12: 18 | F12: =D12*E12/100 -> 0
B13: Other | D13: 0 | E13: 0 | F13: =D13*E13/100 -> 0
B14: Less: Excess Clause @18% | D14: =-Sheet1!G184 -> -859.32 | E14: 18 | F14: =D14*E14/100 -> -154.6776
B15: Less: Salvage Amount @18% | D15: =-Sheet1!G187 -> 0 | E15: 18 | F15: =D15*E15/100 -> 0
C16: Total | D16: =D7+D8+D9+D10+D11+D12+D13+D14+D15 -> -694.07 | F16: 0
C17: GST Excess | D17: 180
C18: GST Salvage | D18: 9
C19: G.TOTAL | D19: =D16+D17+D18 -> -505.07 | F19: 0
B20: GST Amount Entered in Settlement Screen | F20: =SUM(F7:F19) -> -108.4076
C21: Settle Amount | F21: GST
C22: =D19 -> -505.07 | F22: =F20 -> -108.4076
B23: EST_72 Ptovision in INLIAS | E23: Rs. | F23: =C22 -> -505.07
B24: GST Amount Entered in Settlement Screen | E24: Rs. | F24: =F22 -> -108.4076
B25: NET LIABILITY | E25: Rs. | F25: =F23+F24 -> -613.4776
